flagsense/__init__.py
flagsense/flagsense.py
flagsense/version.py
flagsense/lib/__init__.py
flagsense/lib/pymmh3.py
flagsense/model/__init__.py
flagsense/model/fs_flag.py
flagsense/model/fs_user.py
flagsense/model/fs_variation.py
flagsense/services/__init__.py
flagsense/services/event_service.py
flagsense/services/flagsense_service.py
flagsense/services/user_variant_service.py
flagsense/util/__init__.py
flagsense/util/constants.py
flagsense/util/flagsense_error.py
flagsense/util/utility.py
flagsense_sdk-1.0.8.dist-info/LICENSE
flagsense_sdk-1.0.8.dist-info/METADATA
flagsense_sdk-1.0.8.dist-info/WHEEL
flagsense_sdk-1.0.8.dist-info/top_level.txt
flagsense_sdk-1.0.8.dist-info/RECORD
