Metadata-Version: 2.1
Name: flagsense-sdk
Version: 1.0.8
Summary: Flagsense sdk for python
Home-page: https://github.com/flagsense/flagsense-python-sdk
Author: Flagsense
Author-email: senseflag@gmail.com
License: UNKNOWN
Platform: UNKNOWN
Classifier: Programming Language :: Python :: 3
Classifier: License :: OSI Approved :: Apache Software License
Classifier: Operating System :: OS Independent
License-File: LICENSE
Requires-Dist: mmh3 (==2.5.1)
Requires-Dist: packaging (==21.0)
Requires-Dist: requests (>=2.21)
